pyrinth/__init__.py
pyrinth/_util.py
pyrinth/internal/__init__.py
pyrinth/internal/cacheManager.py
pyrinth/internal/lazy.py
pyrinth/internal/sessionManager.py
pyrinth/model/__init__.py
pyrinth/model/license.py
pyrinth/model/v1/__init__.py
pyrinth/model/v1/enums.py
pyrinth/model/v1/mod.py
pyrinth/model/v1/user.py
pyrinth/model/v1/version.py
pyrinth/model/v1/versionFile.py
pyrinth/model/v2/__init__.py
pyrinth/model/v2/_validVersions.py
pyrinth/model/v2/enums.py
pyrinth/model/v2/project.py
pyrinth/model/v2/projectVersion.py
pyrinth/model/v2/searchResult.py
pyrinth/model/v2/user.py
pyrinth/model/v2/versionFile.py
pyrinth-0.1.2.dist-info/LICENSE
pyrinth-0.1.2.dist-info/WHEEL
pyrinth-0.1.2.dist-info/METADATA
pyrinth-0.1.2.dist-info/RECORD
